[
  {
    "chapter": "1",
    "title": "兎と猿のせせらぎ遊び",
    "titleen": "Rabbits and Monkeys Frolicking in the Stream"
  },
  {
    "chapter": "2",
    "title": "兎と蛙の神事弓くらべ",
    "titleen": "Rabbits and Frogs Competing in Ceremonial Archery"
  },
  {
    "chapter": "3",
    "title": "猿僧正、神供を賜る",
    "titleen": "The Monkey High Priest Receiving Ritual Tributes"
  },
  {
    "chapter": "4",
    "title": "猿と蛙の争い",
    "titleen": "Quarrel Between Monkey and Frog"
  },
  {
    "chapter": "5",
    "title": "田楽神事を見守る",
    "titleen": "Spectators at the Dengaku Agricultural Ritual"
  },
  {
    "chapter": "6",
    "title": "兎と蛙の神聖なる相撲",
    "titleen": "The Sacred Sumo Contest Between Rabbit and Frog"
  },
  {
    "chapter": "7",
    "title": "猿、双六盤を運ぶ",
    "titleen": "Monkey Bearing the Sugoroku Game Board"
  },
  {
    "chapter": "8",
    "title": "猿僧正、年忌法要を司る",
    "titleen": "The Monkey High Priest Conducting the Annual Memorial Rites"
  },
  {
    "chapter": "9",
    "title": "猿僧正へ奉げられた供物",
    "titleen": "Sacred Offerings Presented to the Monkey High Priest"
  }
]
